batchspawner/__init__.py
batchspawner/_version.py
batchspawner/api.py
batchspawner/batchspawner.py
batchspawner/singleuser.py
batchspawner-1.3.0.dist-info/LICENSE
batchspawner-1.3.0.dist-info/METADATA
batchspawner-1.3.0.dist-info/WHEEL
batchspawner-1.3.0.dist-info/entry_points.txt
batchspawner-1.3.0.dist-info/top_level.txt
batchspawner-1.3.0.dist-info/RECORD
