Metadata-Version: 2.1
Name: batchspawner
Version: 1.3.0
Summary: Batchspawner: A spawner for Jupyterhub to spawn notebooks using batch resource managers.
Home-page: http://jupyter.org
Author: Michael Milligan, Andrea Zonca, Mike Gilbert
Author-email: milligan@umn.edu
License: BSD
Project-URL: Bug Reports, https://github.com/jupyterhub/batchspawner/issues
Project-URL: Source, https://github.com/jupyterhub/batchspawner/
Project-URL: About Jupyterhub, http://jupyterhub.readthedocs.io/en/latest/
Project-URL: Jupyter Project, http://jupyter.org
Keywords: Interactive,Interpreter,Shell,Web,Jupyter
Platform: Linux
Platform: Mac OS X
Classifier: Intended Audience :: Developers
Classifier: Intended Audience :: System Administrators
Classifier: Intended Audience :: Science/Research
Classifier: License :: OSI Approved :: BSD License
Classifier: Programming Language :: Python
Classifier: Programming Language :: Python :: 3
Requires-Python: >=3.6
License-File: LICENSE
Provides-Extra: test
Requires-Dist: pytest ; extra == 'test'
Requires-Dist: pytest-asyncio ; extra == 'test'
Requires-Dist: pytest-cov ; extra == 'test'
Requires-Dist: notebook ; extra == 'test'
